odoo/addons/stock_account_quantity_history_location/README.rst
odoo/addons/stock_account_quantity_history_location/__init__.py
odoo/addons/stock_account_quantity_history_location/__manifest__.py
odoo/addons/stock_account_quantity_history_location/i18n/stock_account_quantity_history_location.pot
odoo/addons/stock_account_quantity_history_location/readme/CONSTRIBUTORS.rst
odoo/addons/stock_account_quantity_history_location/readme/DESCRIPTION.rst
odoo/addons/stock_account_quantity_history_location/static/description/icon.png
odoo/addons/stock_account_quantity_history_location/static/description/index.html
odoo/addons/stock_account_quantity_history_location/tests/__init__.py
odoo/addons/stock_account_quantity_history_location/tests/test_valuation_location.py
odoo/addons/stock_account_quantity_history_location/wizards/__init__.py
odoo/addons/stock_account_quantity_history_location/wizards/stock_quantity_history.py
odoo/addons/stock_account_quantity_history_location/wizards/stock_quantity_history.xml
odoo12_addon_stock_account_quantity_history_location-12.0.1.1.0.dist-info/METADATA
odoo12_addon_stock_account_quantity_history_location-12.0.1.1.0.dist-info/WHEEL
odoo12_addon_stock_account_quantity_history_location-12.0.1.1.0.dist-info/top_level.txt
odoo12_addon_stock_account_quantity_history_location-12.0.1.1.0.dist-info/RECORD
