Metadata-Version: 2.1
Name: odoo12-addon-stock-account-quantity-history-location
Version: 12.0.1.1.0
Summary: Glue module between Stock Account and Stock Quantity History Location modules
Home-page: https://github.com/OCA/stock-logistics-reporting
Author: Eficent,Odoo Community Association (OCA)
Author-email: support@odoo-community.org
License: AGPL-3
Platform: UNKNOWN
Classifier: Programming Language :: Python
Classifier: Framework :: Odoo
Classifier: License :: OSI Approved :: GNU Affero General Public License v3
Requires-Python: >=3.5
Requires-Dist: odoo12-addon-stock-quantity-history-location
Requires-Dist: odoo (<12.1dev,>=12.0a)
